{
	"$schema": "https://anesis-server.onrender.com/schema/anesis.template.schema.json",
	"name": "solid-vite-js",
	"version": "0.2.1",
	"anesisVersion": ">=0.9.0",
	"author": {
		"name": "Maksym Zhuk",
		"github": "anesis-dev"
	},
	"repository": {
		"type": "github",
		"url": "https://github.com/anesis-dev/templates/tree/main/js/vite/solid",
		"release": "v0.1.0"
	},
	"specialization": "frontend",
	"scope": "web",
	"technologies": ["solid"],
	"buildTool": "vite",
	"languages": ["javascript"],
	"type": "base",
	"metadata": {
		"displayName": "Solid",
		"description": "A modern Solid template for building web applications with Vite using JavaScript.",
		"tags": ["solid", "vite", "javascript", "frontend", "web"]
	}
}
